[{"ocid": "ocds-h6vhtk-003358-integration", "id": "001152-2019", "date": "2019-09-30T14:20:00+01:00", "tag": ["tenderUpdate"], "initiationType": "tender", "tender": {"id": "DN349479", "legalBasis": {"id": "32014L0024", "scheme": "CELEX"}, "title": "regression 3 DPS", "classification": {"scheme": "CPV", "id": "03000000", "description": "Agricultural, farming, fishing, forestry and related products"}, "mainProcurementCategory": "goods", "description": "ghfh", "amendments": [{"id": "1", "unstructuredChanges": [{"oldValue": {"text": ""}, "newValue": {"text": ""}, "where": {"section": "DEFAULT"}}], "description": "vcxv xcvxcv xcvxcvcxv"}]}, "parties": [{"name": "Cumbria County Council", "id": "GB-FTS-545", "identifier": {"legalName": "Cumbria County Council"}, "address": {"streetAddress": "17th Floor, 18 Hague Way", "locality": "Carlisle", "region": "AL", "postalCode": "DT4 5PJ", "countryName": "United Kingdom"}, "contactPoint": {"name": "Mr john 63", "telephone": "+44 3401947110", "email": "divya.rai@proactis.com", "faxNumber": "+44 2161883506"}, "roles": ["buyer"], "details": {"url": "http://www.cumbria.gov.uk/", "buyerProfile": "http://www.cumbria.gov.uk/"}}], "buyer": {"id": "GB-FTS-545", "name": "Cumbria County Council"}, "language": "en"}, {"ocid": "ocds-h6vhtk-003357-integration", "id": "001151-2019", "date": "2019-09-30T11:46:12+01:00", "tag": ["tender"], "initiationType": "tender", "tender": {"id": "DN349479", "legalBasis": {"id": "32014L0024", "scheme": "CELEX"}, "title": "regression 3 DPS", "status": "active", "classification": {"scheme": "CPV", "id": "03000000", "description": "Agricultural, farming, fishing, forestry and related products"}, "mainProcurementCategory": "services", "description": "https://procontract-loadtest.due-north.com", "lots": [{"id": "1", "description": "https://procontract-loadtest.due-north.com", "contractPeriod": {"endDate": "2019-10-23T23:59:59+01:00"}, "hasRenewal": false, "submissionTerms": {"variantPolicy": "notAllowed"}, "hasOptions": false, "status": "active"}], "items": [{"id": "1", "additionalClassifications": [{"scheme": "CPV", "id": "09000000", "description": "Petroleum products, fuel, electricity and other sources of energy"}], "deliveryAddresses": [{"region": "AL"}, {"region": "UK"}], "relatedLot": "1"}], "submissionMethod": ["electronicSubmission", "written"], "submissionMethodDetails": "https://procontract-loadtest.due-north.com", "procurementMethod": "selective", "procurementMethodDetails": "Competitive dialogue", "tenderPeriod": {"endDate": "2019-11-22"}, "submissionTerms": {"languages": ["co"]}, "hasRecurrence": false}, "parties": [{"name": "Cumbria County Council", "id": "GB-FTS-545", "identifier": {"legalName": "Cumbria County Council"}, "address": {"streetAddress": "17th Floor, 18 Hague Way", "locality": "Carlisle", "region": "AL", "postalCode": "DT4 5PJ", "countryName": "United Kingdom"}, "contactPoint": {"name": "Mr john 63", "telephone": "+44 3401947110", "email": "divya.rai@proactis.com", "faxNumber": "+44 2161883506", "url": "https://procontract-loadtest.due-north.com"}, "roles": ["buyer", "centralPurchasingBody"], "details": {"url": "http://www.cumbria.gov.uk/", "buyerProfile": "http://www.cumbria.gov.uk/", "classifications": [{"scheme": "TED_CA_TYPE", "id": "EU_INSTITUTION", "description": "European institution/agency or international organisation"}, {"scheme": "COFOG", "id": "02", "description": "Defence"}]}}, {"name": "https://procontract-loadtest.due-north.com", "id": "GB-FTS-454", "identifier": {"legalName": "https://procontract-loadtest.due-north.com"}, "address": {"locality": "leeds", "countryName": "United Kingdom"}, "roles": ["reviewBody"]}], "buyer": {"id": "GB-FTS-545", "name": "Cumbria County Council"}, "language": "en"}]